<?xml version = '1.0' encoding = 'UTF-8'?>
<Relation class="oracle.dbtools.crest.model.design.logical.Relation" name="Location-location" directorySegmentName="seg_0" id="E784A5D5-9FD1-B71A-7FF4-FF2D3C9634AE">
<createdBy>Piotr</createdBy>
<createdTime>2015-04-15 14:43:39 UTC</createdTime>
<ownerDesignName>commonSheduler_ServerDMD</ownerDesignName>
<engineerTo>
<item key="16D40DF1-1FCE-50F6-B40F-EF7D7DF5423B" value="true"/>
</engineerTo>
<targetPk>686C4B75-A11F-1992-B68D-91A0D1B15DC3</targetPk>
<identifying>false</identifying>
<optionalSource>true</optionalSource>
<optionalTarget>false</optionalTarget>
<sourceCardinality>1</sourceCardinality>
<sourceEntity>6741F8E3-25FE-18A8-FA49-7114D481F8E5</sourceEntity>
<targetCardinalityString>*</targetCardinalityString>
<targetEntity>6741F8E3-25FE-18A8-FA49-7114D481F8E5</targetEntity>
<transferable>true</transferable>
<deleteRule>NO ACTION</deleteRule>
</Relation>